llama_index/readers/markitdown/__init__.py
llama_index/readers/markitdown/base.py
llama_index_readers_markitdown-0.2.1.dist-info/METADATA
llama_index_readers_markitdown-0.2.1.dist-info/WHEEL
llama_index_readers_markitdown-0.2.1.dist-info/licenses/LICENSE
llama_index_readers_markitdown-0.2.1.dist-info/RECORD
