Metadata-Version: 2.4
Name: llama-index-readers-markitdown
Version: 0.2.1
Summary: llama-index readers MarkItDown integration
Author-email: Clelia Astra Bertelli <astraberte9@gmail.com>
Maintainer: AstraBert
License-Expression: MIT
License-File: LICENSE
Requires-Python: <4.0,>=3.10
Requires-Dist: llama-index-core<0.15,>=0.13.0
Requires-Dist: markitdown[all]==0.1.0
